quizli/__init__.py
quizli/examples.py
quizli/layout.py
quizli/main.py
quizli/quiz.py
quizli/session.py
quizli/utils.py
quizli-1.0.0.dist-info/entry_points.txt
quizli-1.0.0.dist-info/WHEEL
quizli-1.0.0.dist-info/METADATA
quizli-1.0.0.dist-info/RECORD
