Metadata-Version: 2.1
Name: quizli
Version: 1.0.0
Summary: An educational project teaching how to open-source an interactive Python quiz app
Home-page: https://github.com/pwenker/quizli
License: MIT
Author: Pascal Wenker
Author-email: pwenker@posteo.de
Requires-Python: >=3.8,<4.0
Classifier: Environment :: Console
Classifier: Intended Audience :: Developers
Classifier: Intended Audience :: Education
Classifier: License :: OSI Approved :: MIT License
Classifier: Natural Language :: English
Classifier: Programming Language :: Python :: 3
Classifier: Programming Language :: Python :: 3 :: Only
Classifier: Programming Language :: Python :: 3.10
Classifier: Programming Language :: Python :: 3.8
Classifier: Programming Language :: Python :: 3.9
Classifier: Topic :: Documentation
Classifier: Topic :: Education
Classifier: Topic :: Software Development
Classifier: Typing :: Typed
Requires-Dist: rich (>=11.0.0,<12.0.0)
Requires-Dist: typer-cli (>=0.0.12,<0.0.13)
Project-URL: Documentation, https://pwenker.github.io/quizli
